adeqt.py
adeqt-0.2.dist-info/LICENSE
adeqt-0.2.dist-info/WHEEL
adeqt-0.2.dist-info/METADATA
adeqt-0.2.dist-info/RECORD
