Metadata-Version: 2.1
Name: adeqt
Version: 0.2
Summary: An interactive Python shell plugin for PyQt & PySide applications
Author-email: Thomas Kluyver <thomas@kluyver.me.uk>
Classifier: License :: OSI Approved :: MIT License
Requires-Dist: qtpy
Requires-Dist: pytest ; extra == "test"
Requires-Dist: pytest-qt ; extra == "test"
Project-URL: Home, https://github.com/takluyver/adeqt
Provides-Extra: test
